them4tch/__init__.py
them4tch/courses.py
them4tch/utils.py
them4tch-0.1.0.dist-info/METADATA
them4tch-0.1.0.dist-info/WHEEL
them4tch-0.1.0.dist-info/top_level.txt
them4tch-0.1.0.dist-info/RECORD
