Metadata-Version: 2.1
Name: them4tch
Version: 0.1.0
Summary: Una biblioteca para consultar los curso de Hack4u
Home-page: https://hack4u.io
Author: Franco Romeo
